{"type": "bubble", "body": {"type": "box", "layout": "vertical", "contents": [{"type": "box", "layout": "vertical", "contents": [{"type": "text", "text": "010.\u52a0\u6263\u5206(\u6383\u5340)", "weight": "bold", "size": "xl"}, {"type": "text", "text": "\u7de8\u8f2f\u7d50\u675f\u8acb\u6309\u7de8\u8f2f\u5b8c\u6210\u9215"}, {"type": "separator", "margin": "md"}]}], "spacing": "xs", "margin": "none"}, "footer": {"type": "box", "layout": "vertical", "contents": [{"type": "button", "action": {"type": "postback", "label": "\u7de8\u8f2f\u5b8c\u6210\u9215", "data": "CleaningEditingPoint&Fin"}, "style": "secondary", "height": "sm"}, {"type": "button", "action": {"type": "postback", "label": "\u4e0d\u7528\u6539\u4e86", "data": "CleaningEndEditPoint"}, "height": "sm"}]}}